{
    "images": [
        {
            "height": 832,
            "width": 832,
            "id": 0,
            "file_name": "opencv_frame_1382.png"
        }
    ],
    "categories": [
        {
            "supercategory": "none",
            "id": 0,
            "name": "None"
        },
        {
            "supercategory": "None",
            "id": 1,
            "name": "Icon"
        }
    ],
    "annotations": [
        {
            "segmentation": [],
            "iscrowd": 0,
            "area": 409.750525090727,
            "image_id": 0,
            "bbox": [
                41.734619140625,
                304.2205505371094,
                20.029186248779297,
                20.457672119140625
            ],
            "category_id": 1,
            "id": 0
        },
        {
            "segmentation": [],
            "iscrowd": 0,
            "area": 344.1185642136261,
            "image_id": 0,
            "bbox": [
                42.689300537109375,
                334.1449279785156,
                19.69647979736328,
                17.4710693359375
            ],
            "category_id": 1,
            "id": 1
        },
        {
            "segmentation": [],
            "iscrowd": 0,
            "area": 369.43150446470827,
            "image_id": 0,
            "bbox": [
                43.094703674316406,
                448.4394836425781,
                20.34707260131836,
                18.156494140625
            ],
            "category_id": 1,
            "id": 2
        },
        {
            "segmentation": [],
            "iscrowd": 0,
            "area": 331.01173853036005,
            "image_id": 0,
            "bbox": [
                43.45638656616211,
                361.2474365234375,
                18.061248779296868,
                18.327178955078125
            ],
            "category_id": 1,
            "id": 3
        },
        {
            "segmentation": [],
            "iscrowd": 0,
            "area": 427.3537758094608,
            "image_id": 0,
            "bbox": [
                42.88994216918945,
                130.10731506347656,
                20.981159210205078,
                20.368453979492188
            ],
            "category_id": 1,
            "id": 4
        },
        {
            "segmentation": [],
            "iscrowd": 0,
            "area": 337.5456730349106,
            "image_id": 0,
            "bbox": [
                44.86955642700195,
                102.3546142578125,
                17.798938751220703,
                18.964370727539062
            ],
            "category_id": 1,
            "id": 5
        },
        {
            "segmentation": [],
            "iscrowd": 0,
            "area": 371.3483982498002,
            "image_id": 0,
            "bbox": [
                45.14049911499024,
                74.59447479248047,
                19.075801849365227,
                19.466987609863295
            ],
            "category_id": 1,
            "id": 6
        },
        {
            "segmentation": [],
            "iscrowd": 0,
            "area": 361.13491636735864,
            "image_id": 0,
            "bbox": [
                42.590293884277344,
                419.9847412109375,
                19.953342437744148,
                18.098968505859375
            ],
            "category_id": 1,
            "id": 7
        },
        {
            "segmentation": [],
            "iscrowd": 0,
            "area": 411.31544661941007,
            "image_id": 0,
            "bbox": [
                41.944374084472656,
                160.3555145263672,
                23.087615966796875,
                17.815414428710938
            ],
            "category_id": 1,
            "id": 8
        },
        {
            "segmentation": [],
            "iscrowd": 0,
            "area": 390.477329762188,
            "image_id": 0,
            "bbox": [
                43.22955322265625,
                475.11566162109375,
                19.513980865478516,
                20.010131835937557
            ],
            "category_id": 1,
            "id": 9
        },
        {
            "segmentation": [],
            "iscrowd": 0,
            "area": 328.7494086553925,
            "image_id": 0,
            "bbox": [
                43.82897186279297,
                218.08297729492188,
                18.332561492919922,
                17.932540893554688
            ],
            "category_id": 1,
            "id": 10
        },
        {
            "segmentation": [],
            "iscrowd": 0,
            "area": 323.6376746178139,
            "image_id": 0,
            "bbox": [
                45.43584442138672,
                390.0137634277344,
                15.278785705566406,
                21.182159423828125
            ],
            "category_id": 1,
            "id": 11
        },
        {
            "segmentation": [],
            "iscrowd": 0,
            "area": 362.22246508975496,
            "image_id": 0,
            "bbox": [
                44.07379531860352,
                274.22412109375,
                17.384250640869134,
                20.83624267578125
            ],
            "category_id": 1,
            "id": 12
        },
        {
            "segmentation": [],
            "iscrowd": 0,
            "area": 226.485591623932,
            "image_id": 0,
            "bbox": [
                46.8945426940918,
                246.62203979492188,
                12.63273620605468,
                17.928466796875
            ],
            "category_id": 1,
            "id": 13
        }
    ]
}