{
    "images": [
        {
            "height": 832,
            "width": 832,
            "id": 0,
            "file_name": "opencv_frame_574.png"
        }
    ],
    "categories": [
        {
            "supercategory": "none",
            "id": 0,
            "name": "None"
        },
        {
            "supercategory": "None",
            "id": 1,
            "name": "Icon"
        },
        {
            "supercategory": "None",
            "id": 2,
            "name": "TextButton"
        }
    ],
    "annotations": [
        {
            "segmentation": [],
            "iscrowd": 0,
            "area": 12255.029062630158,
            "image_id": 0,
            "bbox": [
                48.56780242919922,
                356.3002319335937,
                271.07398223876953,
                45.20916748046881
            ],
            "category_id": 2,
            "id": 0
        },
        {
            "segmentation": [],
            "iscrowd": 0,
            "area": 233.97222496569162,
            "image_id": 0,
            "bbox": [
                51.06853485107422,
                11.544025421142578,
                15.40771484375,
                15.185394287109379
            ],
            "category_id": 1,
            "id": 1
        },
        {
            "segmentation": [],
            "iscrowd": 0,
            "area": 156.45437244715123,
            "image_id": 0,
            "bbox": [
                126.75232696533205,
                11.999812126159668,
                12.453834533691392,
                12.56274700164795
            ],
            "category_id": 1,
            "id": 2
        },
        {
            "segmentation": [],
            "iscrowd": 0,
            "area": 153.73391161859035,
            "image_id": 0,
            "bbox": [
                268.3024597167969,
                11.885116577148438,
                12.97412109375,
                11.849273681640625
            ],
            "category_id": 1,
            "id": 3
        },
        {
            "segmentation": [],
            "iscrowd": 0,
            "area": 159.86652289473574,
            "image_id": 0,
            "bbox": [
                144.77626037597656,
                11.492834091186523,
                12.247543334960938,
                13.052946090698246
            ],
            "category_id": 1,
            "id": 4
        },
        {
            "segmentation": [],
            "iscrowd": 0,
            "area": 127.70204683420175,
            "image_id": 0,
            "bbox": [
                90.46192932128906,
                12.170748710632324,
                10.383415222167983,
                12.298655509948727
            ],
            "category_id": 1,
            "id": 5
        },
        {
            "segmentation": [],
            "iscrowd": 0,
            "area": 131.03255352086836,
            "image_id": 0,
            "bbox": [
                108.5122528076172,
                11.753982543945312,
                10.94979858398436,
                11.966663360595703
            ],
            "category_id": 1,
            "id": 6
        },
        {
            "segmentation": [],
            "iscrowd": 0,
            "area": 139.49384949271882,
            "image_id": 0,
            "bbox": [
                250.89370727539065,
                12.5518159866333,
                11.461334228515597,
                12.170821189880371
            ],
            "category_id": 1,
            "id": 7
        },
        {
            "segmentation": [],
            "iscrowd": 0,
            "area": 123.60923278675186,
            "image_id": 0,
            "bbox": [
                72.25724792480469,
                12.451778411865234,
                10.493438720703125,
                11.779668807983402
            ],
            "category_id": 1,
            "id": 8
        },
        {
            "segmentation": [],
            "iscrowd": 0,
            "area": 219.5159615804951,
            "image_id": 0,
            "bbox": [
                33.54570770263672,
                11.646881103515623,
                15.26986312866211,
                14.37576484680176
            ],
            "category_id": 1,
            "id": 9
        },
        {
            "segmentation": [],
            "iscrowd": 0,
            "area": 113.43907693022629,
            "image_id": 0,
            "bbox": [
                286.0158386230469,
                12.969938278198242,
                10.179473876953125,
                11.143903732299805
            ],
            "category_id": 1,
            "id": 10
        },
        {
            "segmentation": [],
            "iscrowd": 0,
            "area": 101.97174624688343,
            "image_id": 0,
            "bbox": [
                302.0083312988281,
                12.707972526550291,
                8.747650146484375,
                11.657044410705568
            ],
            "category_id": 1,
            "id": 11
        },
        {
            "segmentation": [],
            "iscrowd": 0,
            "area": 131.8845496957798,
            "image_id": 0,
            "bbox": [
                236.7966461181641,
                12.473273277282717,
                10.337844848632784,
                12.757451057434084
            ],
            "category_id": 1,
            "id": 12
        }
    ]
}